toggl/__init__.py
toggl/api_client.py
python_toggl-1.1.0.dist-info/LICENSE
python_toggl-1.1.0.dist-info/METADATA
python_toggl-1.1.0.dist-info/WHEEL
python_toggl-1.1.0.dist-info/top_level.txt
python_toggl-1.1.0.dist-info/RECORD
