Metadata-Version: 2.1
Name: python-toggl
Version: 1.1.0
Summary: Python Wrapper for Toggl API
Home-page: https://github.com/swappsco/toggl-python-api-client
Author: mechastorm
Author-email: dev@swapps.co
License: MIT
Platform: UNKNOWN
License-File: LICENSE
Requires-Dist: requests
